csconverter.py
csconverter-0.2.dist-info/LICENSE.txt
csconverter-0.2.dist-info/METADATA
csconverter-0.2.dist-info/WHEEL
csconverter-0.2.dist-info/top_level.txt
csconverter-0.2.dist-info/RECORD
