Metadata-Version: 2.1
Name: csconverter
Version: 0.2
Summary: ConnectionString Converter library
Home-page: https://github.com/raspher/csconverter
Author: Szymon Scholz
License: UNKNOWN
Keywords: ConnectionString Converter connection string
Platform: UNKNOWN
Classifier: Development Status :: 3 - Alpha
Classifier: Intended Audience :: Developers
Classifier: Topic :: Database
Classifier: Topic :: Software Development :: Libraries :: Python Modules
Classifier: Topic :: Text Processing
Classifier: License :: OSI Approved :: The Unlicense (Unlicense)
Classifier: Operating System :: OS Independent
Classifier: Programming Language :: Python :: 3 :: Only
Requires-Python: >=3.6, <4
License-File: LICENSE.txt
